LICENSE.txt
MANIFEST.in
README.txt
setup.cfg
setup.py
massweb/__init__.py
massweb.egg-info/PKG-INFO
massweb.egg-info/SOURCES.txt
massweb.egg-info/dependency_links.txt
massweb.egg-info/requires.txt
massweb.egg-info/top_level.txt
massweb/fuzz_generators/__init__.py
massweb/fuzz_generators/url_generator.py
massweb/fuzzers/__init__.py
massweb/fuzzers/bsqli_fuzzer.py
massweb/fuzzers/ifuzzer.py
massweb/fuzzers/web_fuzzer.py
massweb/hadoop-utils/massweb_mapper.py
massweb/hadoop-utils/massweb_reducer.py
massweb/hadoop-utils/massweb_simple_reducer.py
massweb/hadoop-utils/out_urls_to_fuzz_1mil
massweb/hadoop-utils/urls_to_fuzz_small
massweb/mass_requests/__init__.py
massweb/mass_requests/mass_request.py
massweb/mass_requests/response_analysis.py
massweb/masscrawler/__init__.py
massweb/masscrawler/masscrawl.py
massweb/payloads/__init__.py
massweb/payloads/bsqli_payload.py
massweb/payloads/bsqli_payload_group.py
massweb/payloads/payload.py
massweb/payloads/payload_group.py
massweb/pnk_net/__init__.py
massweb/pnk_net/find_post.py
massweb/pnk_net/pnk_request.py
massweb/proxy_rotator/__init__.py
massweb/proxy_rotator/proxy_rotate.py
massweb/results/__init__.py
massweb/results/result.py
massweb/targets/__init__.py
massweb/targets/crawl_target.py
massweb/targets/fuzzy_target.py
massweb/targets/fuzzy_target_group.py
massweb/targets/target.py
massweb/vuln_checks/__init__.py
massweb/vuln_checks/check.py
massweb/vuln_checks/match.py
massweb/vuln_checks/mxi.py
massweb/vuln_checks/osci.py
massweb/vuln_checks/sqli.py
massweb/vuln_checks/trav.py
massweb/vuln_checks/xpathi.py
massweb/vuln_checks/xss.py