Metadata-Version: 1.1
Name: massweb
Version: 0.3.1
Summary: Fast Web Fuzzing and Scanning
Home-page: https://bitbucket.org/acaceres/massweb
Author: Alejandro Caceres
Author-email: contact@hyperiongray.com
License: Apache 2.0
Platform: UNKNOWN
Classifier: Development Status :: 4 - Beta
Classifier: Intended Audience :: Developers
Classifier: Programming Language :: Python :: 2.7
Classifier: Programming Language :: Python
